{"moves":[{"target_x":63,"target_y":1064,"type":"move"},{"target_x":76,"target_y":1055,"type":"move"},{"target_x":89,"target_y":1046,"type":"move"},{"target_x":102,"target_y":1037,"type":"move"},{"target_x":115,"target_y":1028,"type":"move"},{"target_x":128,"target_y":1019,"type":"move"},{"target_x":141,"target_y":1010,"type":"move"},{"target_x":154,"target_y":1001,"type":"move"},{"target_x":167,"target_y":992,"type":"move"},{"target_x":180,"target_y":983,"type":"move"},{"target_x":193,"target_y":974,"type":"move"},{"target_x":206,"target_y":965,"type":"move"},{"target_x":219,"target_y":956,"type":"move"},{"target_x":233,"target_y":949,"type":"move"},{"target_x":246,"target_y":940,"type":"move"},{"target_x":260,"target_y":933,"type":"move"},{"target_id":92,"type":"attack"},{"target_id":92,"type":"attack"},{"target_id":92,"type":"attack"},{"target_id":92,"type":"attack"},{"target_id":92,"type":"attack"},{"target_id":92,"type":"attack"},{"target_id":92,"type":"attack"},{"target_id":92,"type":"attack"},{"target_id":95,"type":"attack"},{"target_id":95,"type":"attack"},{"target_id":95,"type":"attack"},{"target_id":95,"type":"attack"},{"target_id":95,"type":"attack"},{"target_x":275,"target_y":929,"type":"move"},{"target_id":93,"type":"attack"},{"target_id":93,"type":"attack"},{"target_id":93,"type":"attack"},{"target_id":93,"type":"attack"},{"target_id":93,"type":"attack"},{"target_id":93,"type":"attack"},{"target_id":93,"type":"attack"},{"target_id":93,"type":"attack"},{"target_id":94,"type":"attack"},{"target_id":94,"type":"attack"},{"target_id":94,"type":"attack"},{"target_id":94,"type":"attack"},{"target_id":94,"type":"attack"},{"target_id":94,"type":"attack"},{"target_id":94,"type":"attack"},{"target_id":94,"type":"attack"},{"target_x":266,"target_y":916,"type":"move"},{"target_x":257,"target_y":903,"type":"move"},{"target_x":248,"target_y":890,"type":"move"},{"target_id":86,"type":"attack"},{"target_id":86,"type":"attack"},{"target_id":86,"type":"attack"},{"target_id":86,"type":"attack"},{"target_id":86,"type":"attack"},{"target_id":86,"type":"attack"},{"target_id":86,"type":"attack"},{"target_id":86,"type":"attack"},{"target_id":85,"type":"attack"},{"target_id":85,"type":"attack"},{"target_id":85,"type":"attack"},{"target_id":85,"type":"attack"},{"target_id":85,"type":"attack"},{"target_id":85,"type":"attack"},{"target_id":85,"type":"attack"},{"target_id":85,"type":"attack"},{"target_id":87,"type":"attack"},{"target_id":87,"type":"attack"},{"target_id":87,"type":"attack"},{"target_id":87,"type":"attack"},{"target_x":248,"target_y":874,"type":"move"},{"target_id":84,"type":"attack"},{"target_id":84,"type":"attack"},{"target_id":84,"type":"attack"},{"target_id":84,"type":"attack"},{"target_id":84,"type":"attack"},{"target_id":84,"type":"attack"},{"target_id":84,"type":"attack"},{"target_id":84,"type":"attack"},{"target_x":235,"target_y":865,"type":"move"},{"target_x":222,"target_y":856,"type":"move"},{"target_x":209,"target_y":847,"type":"move"},{"target_id":107,"type":"attack"},{"target_id":107,"type":"attack"},{"target_id":107,"type":"attack"},{"target_id":107,"type":"attack"},{"target_id":106,"type":"attack"},{"target_id":106,"type":"attack"},{"target_id":106,"type":"attack"},{"target_id":106,"type":"attack"},{"target_id":106,"type":"attack"},{"target_id":106,"type":"attack"},{"target_id":106,"type":"attack"},{"target_x":224,"target_y":839,"type":"move"},{"target_x":239,"target_y":831,"type":"move"},{"target_x":254,"target_y":823,"type":"move"},{"target_x":269,"target_y":815,"type":"move"},{"target_x":284,"target_y":807,"type":"move"},{"target_x":299,"target_y":799,"type":"move"},{"target_x":314,"target_y":791,"type":"move"},{"target_x":329,"target_y":783,"type":"move"},{"target_x":344,"target_y":775,"type":"move"},{"target_x":358,"target_y":766,"type":"move"},{"target_x":372,"target_y":757,"type":"move"},{"target_id":108,"type":"attack"},{"target_id":108,"type":"attack"},{"target_id":108,"type":"attack"},{"target_id":108,"type":"attack"},{"target_id":108,"type":"attack"},{"target_id":108,"type":"attack"},{"target_id":108,"type":"attack"},{"target_id":110,"type":"attack"},{"target_id":110,"type":"attack"},{"target_id":110,"type":"attack"},{"target_id":110,"type":"attack"},{"target_id":110,"type":"attack"},{"target_id":110,"type":"attack"},{"target_id":110,"type":"attack"},{"target_id":111,"type":"attack"},{"target_id":111,"type":"attack"},{"target_id":111,"type":"attack"},{"target_id":111,"type":"attack"},{"target_id":109,"type":"attack"},{"target_id":109,"type":"attack"},{"target_id":109,"type":"attack"},{"target_id":109,"type":"attack"},{"target_id":109,"type":"attack"},{"target_id":109,"type":"attack"},{"target_id":109,"type":"attack"},{"target_x":384,"target_y":769,"type":"move"},{"target_x":396,"target_y":781,"type":"move"},{"target_x":408,"target_y":793,"type":"move"},{"target_x":417,"target_y":807,"type":"move"},{"target_x":426,"target_y":821,"type":"move"},{"target_x":438,"target_y":833,"type":"move"},{"target_x":447,"target_y":847,"type":"move"},{"target_x":459,"target_y":859,"type":"move"},{"target_x":468,"target_y":873,"type":"move"},{"target_x":480,"target_y":885,"type":"move"},{"target_x":489,"target_y":899,"type":"move"},{"target_x":498,"target_y":913,"type":"move"},{"target_id":116,"type":"attack"},{"target_id":116,"type":"attack"},{"target_id":116,"type":"attack"},{"target_id":116,"type":"attack"},{"target_id":116,"type":"attack"},{"target_id":116,"type":"attack"},{"target_id":116,"type":"attack"},{"target_id":117,"type":"attack"},{"target_id":117,"type":"attack"},{"target_id":117,"type":"attack"},{"target_id":117,"type":"attack"},{"target_id":117,"type":"attack"},{"target_id":117,"type":"attack"},{"target_x":502,"target_y":929,"type":"move"},{"target_id":118,"type":"attack"},{"target_id":118,"type":"attack"},{"target_id":118,"type":"attack"},{"target_id":118,"type":"attack"},{"target_id":118,"type":"attack"},{"target_id":118,"type":"attack"},{"target_id":119,"type":"attack"},{"target_id":119,"type":"attack"},{"target_id":119,"type":"attack"},{"target_id":119,"type":"attack"},{"target_x":519,"target_y":929,"type":"move"},{"target_x":535,"target_y":932,"type":"move"},{"target_x":552,"target_y":932,"type":"move"},{"target_x":568,"target_y":935,"type":"move"},{"target_x":585,"target_y":935,"type":"move"},{"target_x":601,"target_y":938,"type":"move"},{"target_x":618,"target_y":938,"type":"move"},{"target_x":634,"target_y":941,"type":"move"},{"target_x":651,"target_y":941,"type":"move"},{"target_x":667,"target_y":944,"type":"move"},{"target_x":684,"target_y":944,"type":"move"},{"target_x":700,"target_y":947,"type":"move"},{"target_x":717,"target_y":947,"type":"move"},{"target_id":142,"type":"attack"},{"target_id":142,"type":"attack"},{"target_id":142,"type":"attack"},{"target_id":142,"type":"attack"},{"target_id":142,"type":"attack"},{"target_id":142,"type":"attack"},{"target_id":143,"type":"attack"},{"target_id":143,"type":"attack"},{"target_id":143,"type":"attack"},{"target_id":143,"type":"attack"},{"target_x":729,"target_y":935,"type":"move"},{"target_x":741,"target_y":923,"type":"move"},{"target_x":753,"target_y":911,"type":"move"},{"target_x":765,"target_y":899,"type":"move"},{"target_x":777,"target_y":887,"type":"move"},{"target_x":789,"target_y":875,"type":"move"},{"target_x":801,"target_y":863,"type":"move"},{"target_x":813,"target_y":851,"type":"move"},{"target_x":825,"target_y":839,"type":"move"},{"target_x":837,"target_y":827,"type":"move"},{"target_x":849,"target_y":815,"type":"move"},{"target_x":861,"target_y":803,"type":"move"},{"target_x":873,"target_y":791,"type":"move"},{"target_x":885,"target_y":779,"type":"move"},{"target_x":897,"target_y":767,"type":"move"},{"target_x":909,"target_y":755,"type":"move"},{"target_x":921,"target_y":743,"type":"move"},{"target_id":148,"type":"attack"},{"target_id":148,"type":"attack"},{"target_id":148,"type":"attack"},{"target_id":148,"type":"attack"},{"target_id":148,"type":"attack"},{"target_id":148,"type":"attack"},{"target_x":921,"target_y":725,"type":"move"},{"target_id":151,"type":"attack"},{"target_id":151,"type":"attack"},{"target_id":151,"type":"attack"},{"target_x":913,"target_y":709,"type":"move"},{"target_x":905,"target_y":693,"type":"move"},{"target_x":894,"target_y":679,"type":"move"},{"target_x":886,"target_y":663,"type":"move"},{"target_x":875,"target_y":649,"type":"move"},{"target_x":867,"target_y":633,"type":"move"},{"target_x":856,"target_y":619,"type":"move"},{"target_x":848,"target_y":603,"type":"move"},{"target_x":837,"target_y":589,"type":"move"},{"target_x":829,"target_y":573,"type":"move"},{"target_id":78,"type":"attack"},{"target_id":78,"type":"attack"},{"target_id":78,"type":"attack"},{"target_id":78,"type":"attack"},{"target_id":78,"type":"attack"},{"target_id":78,"type":"attack"},{"target_id":78,"type":"attack"},{"target_id":78,"type":"attack"},{"target_id":78,"type":"attack"},{"target_id":78,"type":"attack"},{"target_id":78,"type":"attack"},{"target_id":78,"type":"attack"},{"target_id":78,"type":"attack"},{"target_id":79,"type":"attack"},{"target_id":79,"type":"attack"},{"target_id":79,"type":"attack"},{"target_id":79,"type":"attack"},{"target_id":79,"type":"attack"},{"target_id":79,"type":"attack"},{"target_id":79,"type":"attack"},{"target_id":79,"type":"attack"},{"target_id":79,"type":"attack"},{"target_id":79,"type":"attack"},{"target_id":79,"type":"attack"},{"target_id":79,"type":"attack"},{"target_id":79,"type":"attack"},{"target_id":80,"type":"attack"},{"target_id":80,"type":"attack"},{"target_id":80,"type":"attack"},{"target_id":80,"type":"attack"},{"target_id":80,"type":"attack"},{"target_id":80,"type":"attack"},{"target_id":80,"type":"attack"},{"target_id":80,"type":"attack"},{"target_id":80,"type":"attack"},{"target_id":80,"type":"attack"},{"target_id":80,"type":"attack"},{"target_id":80,"type":"attack"},{"target_x":821,"target_y":557,"type":"move"},{"target_x":813,"target_y":541,"type":"move"},{"target_x":805,"target_y":525,"type":"move"},{"target_x":797,"target_y":509,"type":"move"},{"target_x":789,"target_y":493,"type":"move"},{"target_x":781,"target_y":477,"type":"move"},{"target_x":773,"target_y":461,"type":"move"},{"target_x":765,"target_y":445,"type":"move"},{"target_x":757,"target_y":429,"type":"move"},{"target_x":749,"target_y":413,"type":"move"},{"target_x":741,"target_y":397,"type":"move"},{"target_id":115,"type":"attack"},{"target_id":115,"type":"attack"},{"target_id":115,"type":"attack"},{"target_x":727,"target_y":408,"type":"move"},{"target_x":714,"target_y":420,"type":"move"},{"target_x":701,"target_y":432,"type":"move"},{"target_x":688,"target_y":444,"type":"move"},{"target_x":675,"target_y":456,"type":"move"},{"target_x":663,"target_y":469,"type":"move"},{"target_x":650,"target_y":481,"type":"move"},{"target_x":638,"target_y":494,"type":"move"},{"target_id":139,"type":"attack"},{"target_id":139,"type":"attack"},{"target_id":139,"type":"attack"},{"target_id":138,"type":"attack"},{"target_id":138,"type":"attack"},{"target_id":138,"type":"attack"},{"target_id":138,"type":"attack"},{"target_id":138,"type":"attack"},{"target_id":138,"type":"attack"},{"target_x":623,"target_y":505,"type":"move"},{"target_x":608,"target_y":516,"type":"move"},{"target_x":593,"target_y":527,"type":"move"},{"target_x":578,"target_y":538,"type":"move"},{"target_x":563,"target_y":549,"type":"move"},{"target_x":548,"target_y":560,"type":"move"},{"target_x":534,"target_y":572,"type":"move"},{"target_x":520,"target_y":584,"type":"move"},{"target_x":506,"target_y":596,"type":"move"},{"target_x":492,"target_y":608,"type":"move"},{"target_id":134,"type":"attack"},{"target_id":134,"type":"attack"},{"target_id":134,"type":"attack"},{"target_id":134,"type":"attack"},{"target_id":134,"type":"attack"},{"target_id":135,"type":"attack"},{"target_id":135,"type":"attack"},{"target_id":135,"type":"attack"},{"target_id":133,"type":"attack"},{"target_id":133,"type":"attack"},{"target_id":133,"type":"attack"},{"target_id":133,"type":"attack"},{"target_id":133,"type":"attack"},{"target_x":474,"target_y":604,"type":"move"},{"target_x":456,"target_y":600,"type":"move"},{"target_x":438,"target_y":596,"type":"move"},{"target_x":420,"target_y":592,"type":"move"},{"target_x":402,"target_y":588,"type":"move"},{"target_x":384,"target_y":584,"type":"move"},{"target_x":366,"target_y":581,"type":"move"},{"target_x":348,"target_y":578,"type":"move"},{"target_x":330,"target_y":575,"type":"move"},{"target_x":311,"target_y":575,"type":"move"},{"target_id":75,"type":"attack"},{"target_id":75,"type":"attack"},{"target_id":75,"type":"attack"},{"target_id":75,"type":"attack"},{"target_id":75,"type":"attack"},{"target_id":75,"type":"attack"},{"target_id":75,"type":"attack"},{"target_id":75,"type":"attack"},{"target_id":75,"type":"attack"},{"target_id":75,"type":"attack"},{"target_x":295,"target_y":565,"type":"move"},{"target_id":77,"type":"attack"},{"target_id":77,"type":"attack"},{"target_id":77,"type":"attack"},{"target_id":77,"type":"attack"},{"target_id":77,"type":"attack"},{"target_id":77,"type":"attack"},{"target_id":77,"type":"attack"},{"target_id":77,"type":"attack"},{"target_id":77,"type":"attack"},{"target_id":77,"type":"attack"},{"target_id":77,"type":"attack"},{"target_x":279,"target_y":575,"type":"move"},{"target_id":76,"type":"attack"},{"target_id":76,"type":"attack"},{"target_id":76,"type":"attack"},{"target_id":76,"type":"attack"},{"target_id":76,"type":"attack"},{"target_id":76,"type":"attack"},{"target_id":76,"type":"attack"},{"target_id":76,"type":"attack"},{"target_id":76,"type":"attack"},{"target_id":76,"type":"attack"},{"target_x":262,"target_y":583,"type":"move"},{"target_x":245,"target_y":591,"type":"move"},{"target_x":228,"target_y":599,"type":"move"},{"target_x":212,"target_y":609,"type":"move"},{"target_id":128,"type":"attack"},{"target_id":128,"type":"attack"},{"target_id":128,"type":"attack"},{"target_id":128,"type":"attack"},{"target_id":128,"type":"attack"},{"target_id":131,"type":"attack"},{"target_id":131,"type":"attack"},{"target_id":131,"type":"attack"},{"target_x":208,"target_y":591,"type":"move"},{"target_x":204,"target_y":573,"type":"move"},{"target_x":201,"target_y":555,"type":"move"},{"target_x":198,"target_y":537,"type":"move"},{"target_x":195,"target_y":519,"type":"move"},{"target_x":192,"target_y":501,"type":"move"},{"target_x":189,"target_y":483,"type":"move"},{"target_x":186,"target_y":465,"type":"move"},{"target_x":186,"target_y":446,"type":"move"},{"target_x":183,"target_y":428,"type":"move"},{"target_x":183,"target_y":409,"type":"move"},{"target_id":152,"type":"attack"},{"target_id":152,"type":"attack"},{"target_id":152,"type":"attack"},{"target_id":152,"type":"attack"},{"target_id":152,"type":"attack"},{"target_id":155,"type":"attack"},{"target_id":155,"type":"attack"},{"target_id":155,"type":"attack"},{"target_id":153,"type":"attack"},{"target_id":153,"type":"attack"},{"target_id":153,"type":"attack"},{"target_id":153,"type":"attack"},{"target_id":153,"type":"attack"},{"target_id":154,"type":"attack"},{"target_id":154,"type":"attack"},{"target_id":154,"type":"attack"},{"target_id":154,"type":"attack"},{"target_id":154,"type":"attack"},{"target_x":177,"target_y":391,"type":"move"},{"target_x":171,"target_y":373,"type":"move"},{"target_x":165,"target_y":355,"type":"move"},{"target_x":159,"target_y":337,"type":"move"},{"target_x":153,"target_y":319,"type":"move"},{"target_x":148,"target_y":301,"type":"move"},{"target_x":143,"target_y":283,"type":"move"},{"target_x":138,"target_y":265,"type":"move"},{"target_x":133,"target_y":247,"type":"move"},{"target_x":128,"target_y":229,"type":"move"},{"target_x":123,"target_y":211,"type":"move"},{"target_x":118,"target_y":193,"type":"move"},{"target_x":113,"target_y":175,"type":"move"},{"target_x":109,"target_y":157,"type":"move"},{"target_x":105,"target_y":139,"type":"move"},{"target_x":102,"target_y":121,"type":"move"},{"target_id":156,"type":"attack"},{"target_id":156,"type":"attack"},{"target_id":156,"type":"attack"},{"target_id":156,"type":"attack"},{"target_id":156,"type":"attack"},{"target_id":156,"type":"attack"},{"target_id":156,"type":"attack"},{"target_id":156,"type":"attack"},{"target_id":156,"type":"attack"},{"target_id":156,"type":"attack"},{"target_id":156,"type":"attack"},{"target_id":156,"type":"attack"},{"target_id":156,"type":"attack"},{"target_id":156,"type":"attack"},{"target_id":156,"type":"attack"},{"target_id":156,"type":"attack"},{"target_id":156,"type":"attack"},{"target_id":156,"type":"attack"},{"target_id":156,"type":"attack"},{"target_id":156,"type":"attack"},{"target_id":156,"type":"attack"},{"target_id":156,"type":"attack"},{"target_id":156,"type":"attack"},{"target_id":156,"type":"attack"},{"target_id":156,"type":"attack"},{"target_id":156,"type":"attack"},{"target_id":156,"type":"attack"},{"target_id":156,"type":"attack"},{"target_id":156,"type":"attack"},{"target_id":156,"type":"attack"},{"target_id":156,"type":"attack"},{"target_id":156,"type":"attack"},{"target_id":156,"type":"attack"},{"target_id":156,"type":"attack"},{"target_id":156,"type":"attack"},{"target_id":156,"type":"attack"},{"target_id":156,"type":"attack"},{"target_id":156,"type":"attack"},{"target_id":156,"type":"attack"},{"target_id":156,"type":"attack"},{"target_id":156,"type":"attack"},{"target_id":156,"type":"attack"},{"target_id":156,"type":"attack"},{"target_id":156,"type":"attack"},{"target_id":156,"type":"attack"},{"target_id":156,"type":"attack"},{"target_id":156,"type":"attack"},{"target_id":156,"type":"attack"},{"target_id":156,"type":"attack"},{"target_id":156,"type":"attack"},{"target_id":156,"type":"attack"},{"target_id":156,"type":"attack"},{"target_id":156,"type":"attack"},{"target_id":156,"type":"attack"},{"target_id":156,"type":"attack"},{"target_id":156,"type":"attack"},{"target_id":156,"type":"attack"},{"target_id":156,"type":"attack"},{"target_id":156,"type":"attack"},{"target_id":156,"type":"attack"},{"target_id":156,"type":"attack"},{"target_id":156,"type":"attack"},{"target_id":156,"type":"attack"},{"target_id":156,"type":"attack"},{"target_id":156,"type":"attack"},{"target_id":156,"type":"attack"},{"target_id":156,"type":"attack"},{"target_id":156,"type":"attack"},{"target_id":156,"type":"attack"},{"target_id":156,"type":"attack"},{"target_id":156,"type":"attack"},{"target_id":156,"type":"attack"},{"target_id":156,"type":"attack"},{"target_id":156,"type":"attack"},{"target_id":156,"type":"attack"},{"target_id":156,"type":"attack"},{"target_id":156,"type":"attack"},{"target_id":156,"type":"attack"},{"target_id":156,"type":"attack"},{"target_id":156,"type":"attack"},{"target_id":156,"type":"attack"},{"target_id":156,"type":"attack"},{"target_id":156,"type":"attack"},{"target_id":156,"type":"attack"}]}