{"moves":[{"target_x":936,"target_y":747,"type":"move"},{"target_x":901,"target_y":724,"type":"move"},{"target_x":867,"target_y":700,"type":"move"},{"target_x":833,"target_y":676,"type":"move"},{"target_x":799,"target_y":652,"type":"move"},{"target_x":765,"target_y":628,"type":"move"},{"target_x":731,"target_y":604,"type":"move"},{"target_x":697,"target_y":580,"type":"move"},{"target_x":663,"target_y":556,"type":"move"},{"target_x":629,"target_y":532,"type":"move"},{"target_x":595,"target_y":508,"type":"move"},{"target_x":561,"target_y":484,"type":"move"},{"target_x":527,"target_y":460,"type":"move"},{"target_x":495,"target_y":433,"type":"move"},{"target_x":461,"target_y":409,"type":"move"},{"target_x":429,"target_y":382,"type":"move"},{"target_x":397,"target_y":360,"type":"move"},{"target_id":0,"type":"attack"},{"target_id":0,"type":"attack"},{"target_id":0,"type":"attack"},{"target_id":0,"type":"attack"},{"target_id":0,"type":"attack"},{"target_id":0,"type":"attack"},{"target_id":0,"type":"attack"},{"target_id":0,"type":"attack"},{"target_id":0,"type":"attack"},{"target_id":0,"type":"attack"},{"target_id":0,"type":"attack"},{"target_id":0,"type":"attack"},{"target_id":0,"type":"attack"},{"target_id":0,"type":"attack"},{"target_id":0,"type":"attack"},{"target_id":0,"type":"attack"},{"target_id":0,"type":"attack"},{"target_id":0,"type":"attack"},{"target_id":0,"type":"attack"},{"target_id":0,"type":"attack"},{"target_id":0,"type":"attack"},{"target_id":0,"type":"attack"},{"target_id":0,"type":"attack"},{"target_id":0,"type":"attack"},{"target_id":0,"type":"attack"},{"target_id":0,"type":"attack"},{"target_id":0,"type":"attack"},{"target_id":0,"type":"attack"},{"target_id":1,"type":"attack"},{"target_id":1,"type":"attack"},{"target_id":1,"type":"attack"},{"target_id":1,"type":"attack"},{"target_id":1,"type":"attack"},{"target_id":1,"type":"attack"},{"target_id":1,"type":"attack"},{"target_id":1,"type":"attack"},{"target_id":1,"type":"attack"},{"target_id":1,"type":"attack"},{"target_id":1,"type":"attack"},{"target_id":1,"type":"attack"},{"target_id":1,"type":"attack"},{"target_id":1,"type":"attack"},{"target_id":1,"type":"attack"},{"target_id":1,"type":"attack"},{"target_id":2,"type":"attack"},{"target_id":2,"type":"attack"},{"target_id":2,"type":"attack"},{"target_id":2,"type":"attack"},{"target_id":2,"type":"attack"},{"target_id":2,"type":"attack"},{"target_id":2,"type":"attack"},{"target_id":2,"type":"attack"},{"target_id":2,"type":"attack"},{"target_id":2,"type":"attack"},{"target_id":2,"type":"attack"},{"target_id":2,"type":"attack"},{"target_id":2,"type":"attack"},{"target_id":2,"type":"attack"},{"target_id":2,"type":"attack"},{"target_id":3,"type":"attack"},{"target_id":3,"type":"attack"},{"target_id":3,"type":"attack"},{"target_id":3,"type":"attack"},{"target_id":3,"type":"attack"},{"target_id":3,"type":"attack"},{"target_id":3,"type":"attack"},{"target_id":3,"type":"attack"},{"target_id":3,"type":"attack"},{"target_id":3,"type":"attack"},{"target_id":3,"type":"attack"},{"target_id":4,"type":"attack"},{"target_id":4,"type":"attack"},{"target_id":4,"type":"attack"},{"target_id":4,"type":"attack"},{"target_id":4,"type":"attack"},{"target_id":4,"type":"attack"},{"target_id":4,"type":"attack"},{"target_id":4,"type":"attack"},{"target_id":4,"type":"attack"},{"target_id":4,"type":"attack"},{"target_id":4,"type":"attack"},{"target_id":4,"type":"attack"},{"target_id":4,"type":"attack"},{"target_id":4,"type":"attack"},{"target_id":4,"type":"attack"},{"target_x":416,"target_y":341,"type":"move"},{"target_id":5,"type":"attack"},{"target_id":5,"type":"attack"},{"target_id":5,"type":"attack"},{"target_id":5,"type":"attack"},{"target_id":5,"type":"attack"},{"target_id":5,"type":"attack"},{"target_id":5,"type":"attack"},{"target_id":5,"type":"attack"},{"target_id":5,"type":"attack"},{"target_id":5,"type":"attack"},{"target_id":5,"type":"attack"},{"target_id":5,"type":"attack"},{"target_id":5,"type":"attack"},{"target_id":5,"type":"attack"},{"target_id":5,"type":"attack"},{"target_id":5,"type":"attack"},{"target_id":5,"type":"attack"},{"target_id":5,"type":"attack"},{"target_id":6,"type":"attack"},{"target_id":6,"type":"attack"},{"target_id":6,"type":"attack"},{"target_id":6,"type":"attack"},{"target_id":6,"type":"attack"},{"target_id":7,"type":"attack"},{"target_id":7,"type":"attack"},{"target_id":7,"type":"attack"},{"target_id":7,"type":"attack"},{"target_id":7,"type":"attack"},{"target_id":7,"type":"attack"},{"target_id":7,"type":"attack"},{"target_id":7,"type":"attack"},{"target_id":7,"type":"attack"},{"target_id":7,"type":"attack"},{"target_id":7,"type":"attack"},{"target_id":7,"type":"attack"},{"target_x":424,"target_y":382,"type":"move"},{"target_x":432,"target_y":423,"type":"move"},{"target_x":440,"target_y":464,"type":"move"},{"target_x":448,"target_y":505,"type":"move"},{"target_x":456,"target_y":546,"type":"move"},{"target_x":464,"target_y":587,"type":"move"},{"target_x":472,"target_y":628,"type":"move"},{"target_x":480,"target_y":669,"type":"move"},{"target_x":488,"target_y":710,"type":"move"},{"target_x":496,"target_y":751,"type":"move"},{"target_x":504,"target_y":792,"type":"move"},{"target_x":512,"target_y":833,"type":"move"},{"target_x":519,"target_y":874,"type":"move"},{"target_x":526,"target_y":915,"type":"move"},{"target_x":533,"target_y":956,"type":"move"},{"target_x":540,"target_y":997,"type":"move"},{"target_x":547,"target_y":1038,"type":"move"},{"target_x":554,"target_y":1079,"type":"move"},{"target_x":561,"target_y":1120,"type":"move"},{"target_x":567,"target_y":1161,"type":"move"},{"target_x":573,"target_y":1202,"type":"move"},{"target_x":578,"target_y":1243,"type":"move"},{"target_id":8,"type":"attack"},{"target_id":8,"type":"attack"},{"target_id":8,"type":"attack"},{"target_id":8,"type":"attack"},{"target_id":8,"type":"attack"},{"target_id":8,"type":"attack"},{"target_id":8,"type":"attack"},{"target_id":8,"type":"attack"},{"target_id":8,"type":"attack"},{"target_id":8,"type":"attack"},{"target_id":8,"type":"attack"},{"target_id":8,"type":"attack"},{"target_id":8,"type":"attack"},{"target_id":8,"type":"attack"},{"target_id":8,"type":"attack"},{"target_id":8,"type":"attack"},{"target_id":8,"type":"attack"},{"target_id":8,"type":"attack"},{"target_id":8,"type":"attack"},{"target_id":8,"type":"attack"},{"target_id":8,"type":"attack"},{"target_id":8,"type":"attack"},{"target_id":8,"type":"attack"},{"target_id":8,"type":"attack"},{"target_x":601,"target_y":1278,"type":"move"},{"target_id":9,"type":"attack"},{"target_id":9,"type":"attack"},{"target_id":9,"type":"attack"},{"target_id":9,"type":"attack"},{"target_id":9,"type":"attack"},{"target_id":9,"type":"attack"},{"target_id":9,"type":"attack"},{"target_id":9,"type":"attack"},{"target_id":9,"type":"attack"},{"target_id":9,"type":"attack"},{"target_id":9,"type":"attack"},{"target_id":9,"type":"attack"},{"target_id":9,"type":"attack"},{"target_id":9,"type":"attack"},{"target_id":9,"type":"attack"},{"target_id":9,"type":"attack"},{"target_id":10,"type":"attack"},{"target_id":10,"type":"attack"},{"target_id":10,"type":"attack"},{"target_id":10,"type":"attack"},{"target_id":10,"type":"attack"},{"target_id":10,"type":"attack"},{"target_x":589,"target_y":1246,"type":"move"},{"target_id":11,"type":"attack"},{"target_id":11,"type":"attack"},{"target_id":11,"type":"attack"},{"target_id":11,"type":"attack"},{"target_id":11,"type":"attack"},{"target_id":11,"type":"attack"},{"target_id":11,"type":"attack"},{"target_id":11,"type":"attack"},{"target_id":11,"type":"attack"},{"target_id":11,"type":"attack"},{"target_id":12,"type":"attack"},{"target_id":12,"type":"attack"},{"target_id":12,"type":"attack"},{"target_id":12,"type":"attack"},{"target_id":12,"type":"attack"},{"target_id":12,"type":"attack"},{"target_id":12,"type":"attack"},{"target_id":12,"type":"attack"},{"target_id":12,"type":"attack"},{"target_id":12,"type":"attack"},{"target_x":578,"target_y":1278,"type":"move"},{"target_id":13,"type":"attack"},{"target_id":13,"type":"attack"},{"target_id":13,"type":"attack"},{"target_id":13,"type":"attack"},{"target_id":13,"type":"attack"},{"target_id":13,"type":"attack"},{"target_id":13,"type":"attack"},{"target_id":13,"type":"attack"},{"target_id":13,"type":"attack"},{"target_id":13,"type":"attack"},{"target_id":13,"type":"attack"},{"target_id":13,"type":"attack"},{"target_id":14,"type":"attack"},{"target_id":14,"type":"attack"},{"target_id":14,"type":"attack"},{"target_id":14,"type":"attack"},{"target_x":574,"target_y":1228,"type":"move"},{"target_x":570,"target_y":1178,"type":"move"},{"target_x":566,"target_y":1128,"type":"move"},{"target_x":562,"target_y":1078,"type":"move"},{"target_x":558,"target_y":1028,"type":"move"},{"target_x":554,"target_y":978,"type":"move"},{"target_x":550,"target_y":928,"type":"move"},{"target_x":546,"target_y":878,"type":"move"},{"target_x":542,"target_y":828,"type":"move"},{"target_x":539,"target_y":778,"type":"move"},{"target_x":536,"target_y":728,"type":"move"},{"target_x":533,"target_y":678,"type":"move"},{"target_x":533,"target_y":627,"type":"move"},{"target_id":15,"type":"attack"},{"target_id":15,"type":"attack"},{"target_id":15,"type":"attack"},{"target_id":15,"type":"attack"},{"target_id":15,"type":"attack"},{"target_id":15,"type":"attack"},{"target_id":15,"type":"attack"},{"target_id":15,"type":"attack"},{"target_id":15,"type":"attack"},{"target_id":15,"type":"attack"},{"target_id":15,"type":"attack"},{"target_id":15,"type":"attack"},{"target_id":15,"type":"attack"},{"target_id":15,"type":"attack"},{"target_id":15,"type":"attack"},{"target_id":15,"type":"attack"},{"target_id":15,"type":"attack"},{"target_id":15,"type":"attack"},{"target_id":15,"type":"attack"},{"target_id":15,"type":"attack"},{"target_id":15,"type":"attack"},{"target_id":15,"type":"attack"},{"target_id":15,"type":"attack"},{"target_id":15,"type":"attack"},{"target_id":15,"type":"attack"},{"target_id":15,"type":"attack"},{"target_id":15,"type":"attack"},{"target_id":15,"type":"attack"},{"target_x":553,"target_y":591,"type":"move"},{"target_id":16,"type":"attack"},{"target_id":16,"type":"attack"},{"target_id":16,"type":"attack"},{"target_id":16,"type":"attack"},{"target_id":16,"type":"attack"},{"target_id":16,"type":"attack"},{"target_id":16,"type":"attack"},{"target_id":16,"type":"attack"},{"target_id":16,"type":"attack"},{"target_id":16,"type":"attack"},{"target_id":16,"type":"attack"},{"target_id":16,"type":"attack"},{"target_id":16,"type":"attack"},{"target_id":16,"type":"attack"},{"target_id":17,"type":"attack"},{"target_id":17,"type":"attack"},{"target_id":17,"type":"attack"},{"target_id":17,"type":"attack"},{"target_id":17,"type":"attack"},{"target_id":18,"type":"attack"},{"target_id":18,"type":"attack"},{"target_id":18,"type":"attack"},{"target_id":18,"type":"attack"},{"target_id":19,"type":"attack"},{"target_id":19,"type":"attack"},{"target_id":19,"type":"attack"},{"target_id":19,"type":"attack"},{"target_id":19,"type":"attack"},{"target_id":19,"type":"attack"},{"target_id":19,"type":"attack"},{"target_id":20,"type":"attack"},{"target_id":20,"type":"attack"},{"target_id":20,"type":"attack"},{"target_id":20,"type":"attack"},{"target_id":20,"type":"attack"},{"target_id":21,"type":"attack"},{"target_id":21,"type":"attack"},{"target_id":21,"type":"attack"},{"target_id":21,"type":"attack"},{"target_id":21,"type":"attack"},{"target_id":21,"type":"attack"},{"target_id":21,"type":"attack"},{"target_id":21,"type":"attack"},{"target_id":21,"type":"attack"},{"target_id":21,"type":"attack"},{"target_id":21,"type":"attack"},{"target_id":21,"type":"attack"},{"target_id":21,"type":"attack"},{"target_id":22,"type":"attack"},{"target_id":22,"type":"attack"},{"target_id":22,"type":"attack"},{"target_id":22,"type":"attack"},{"target_id":22,"type":"attack"},{"target_id":22,"type":"attack"},{"target_x":603,"target_y":588,"type":"move"},{"target_x":653,"target_y":585,"type":"move"},{"target_x":703,"target_y":585,"type":"move"},{"target_id":23,"type":"attack"},{"target_id":23,"type":"attack"},{"target_id":23,"type":"attack"},{"target_id":23,"type":"attack"},{"target_id":23,"type":"attack"},{"target_id":23,"type":"attack"},{"target_id":23,"type":"attack"},{"target_id":23,"type":"attack"},{"target_id":23,"type":"attack"},{"target_id":23,"type":"attack"},{"target_id":23,"type":"attack"},{"target_id":23,"type":"attack"},{"target_id":23,"type":"attack"},{"target_id":23,"type":"attack"},{"target_id":23,"type":"attack"},{"target_id":23,"type":"attack"},{"target_id":23,"type":"attack"},{"target_id":23,"type":"attack"},{"target_id":23,"type":"attack"},{"target_id":23,"type":"attack"},{"target_id":23,"type":"attack"},{"target_id":24,"type":"attack"},{"target_id":24,"type":"attack"},{"target_id":24,"type":"attack"},{"target_id":24,"type":"attack"},{"target_id":24,"type":"attack"},{"target_id":24,"type":"attack"},{"target_id":24,"type":"attack"},{"target_id":24,"type":"attack"},{"target_id":24,"type":"attack"},{"target_id":24,"type":"attack"},{"target_id":24,"type":"attack"},{"target_id":24,"type":"attack"},{"target_id":24,"type":"attack"},{"target_id":24,"type":"attack"},{"target_id":24,"type":"attack"},{"target_id":24,"type":"attack"},{"target_id":25,"type":"attack"},{"target_id":25,"type":"attack"},{"target_id":25,"type":"attack"},{"target_id":25,"type":"attack"},{"target_id":25,"type":"attack"},{"target_id":26,"type":"attack"},{"target_id":26,"type":"attack"},{"target_id":26,"type":"attack"},{"target_id":26,"type":"attack"},{"target_id":27,"type":"attack"},{"target_id":27,"type":"attack"},{"target_id":27,"type":"attack"},{"target_id":27,"type":"attack"},{"target_id":27,"type":"attack"},{"target_id":27,"type":"attack"},{"target_id":27,"type":"attack"},{"target_id":27,"type":"attack"},{"target_id":27,"type":"attack"},{"target_id":27,"type":"attack"},{"target_id":27,"type":"attack"},{"target_id":27,"type":"attack"},{"target_id":28,"type":"attack"},{"target_id":28,"type":"attack"},{"target_id":28,"type":"attack"},{"target_id":28,"type":"attack"},{"target_id":28,"type":"attack"},{"target_id":28,"type":"attack"},{"target_id":29,"type":"attack"},{"target_id":29,"type":"attack"},{"target_id":29,"type":"attack"},{"target_x":731,"target_y":638,"type":"move"},{"target_x":759,"target_y":691,"type":"move"},{"target_x":787,"target_y":744,"type":"move"},{"target_x":815,"target_y":797,"type":"move"},{"target_x":846,"target_y":848,"type":"move"},{"target_x":874,"target_y":901,"type":"move"},{"target_x":905,"target_y":952,"type":"move"},{"target_x":933,"target_y":1005,"type":"move"},{"target_x":964,"target_y":1056,"type":"move"},{"target_x":992,"target_y":1109,"type":"move"},{"target_x":1023,"target_y":1160,"type":"move"},{"target_x":1051,"target_y":1213,"type":"move"},{"target_x":1082,"target_y":1264,"type":"move"},{"target_x":1110,"target_y":1317,"type":"move"},{"target_x":1141,"target_y":1368,"type":"move"},{"target_x":1169,"target_y":1421,"type":"move"},{"target_x":1197,"target_y":1474,"type":"move"},{"target_id":30,"type":"attack"},{"target_id":30,"type":"attack"},{"target_id":30,"type":"attack"},{"target_id":30,"type":"attack"},{"target_id":30,"type":"attack"},{"target_id":30,"type":"attack"},{"target_id":30,"type":"attack"},{"target_id":30,"type":"attack"},{"target_id":30,"type":"attack"},{"target_id":30,"type":"attack"},{"target_id":30,"type":"attack"},{"target_id":30,"type":"attack"},{"target_id":30,"type":"attack"},{"target_id":30,"type":"attack"},{"target_id":30,"type":"attack"},{"target_id":30,"type":"attack"},{"target_id":30,"type":"attack"},{"target_id":30,"type":"attack"},{"target_id":30,"type":"attack"},{"target_id":31,"type":"attack"},{"target_id":31,"type":"attack"},{"target_id":31,"type":"attack"},{"target_id":31,"type":"attack"},{"target_id":31,"type":"attack"},{"target_id":31,"type":"attack"},{"target_id":31,"type":"attack"},{"target_id":31,"type":"attack"},{"target_id":31,"type":"attack"},{"target_id":31,"type":"attack"},{"target_id":32,"type":"attack"},{"target_id":32,"type":"attack"},{"target_id":32,"type":"attack"},{"target_id":32,"type":"attack"},{"target_id":32,"type":"attack"},{"target_id":32,"type":"attack"},{"target_id":32,"type":"attack"},{"target_id":32,"type":"attack"},{"target_id":32,"type":"attack"},{"target_id":32,"type":"attack"},{"target_id":32,"type":"attack"},{"target_id":32,"type":"attack"},{"target_id":33,"type":"attack"},{"target_id":33,"type":"attack"},{"target_id":33,"type":"attack"},{"target_id":33,"type":"attack"},{"target_id":33,"type":"attack"},{"target_id":33,"type":"attack"},{"target_id":33,"type":"attack"},{"target_id":33,"type":"attack"},{"target_id":33,"type":"attack"},{"target_id":33,"type":"attack"},{"target_id":33,"type":"attack"},{"target_id":33,"type":"attack"},{"target_id":34,"type":"attack"},{"target_id":34,"type":"attack"},{"target_id":34,"type":"attack"},{"target_id":34,"type":"attack"},{"target_id":34,"type":"attack"},{"target_id":34,"type":"attack"},{"target_id":34,"type":"attack"},{"target_id":34,"type":"attack"},{"target_id":35,"type":"attack"},{"target_id":35,"type":"attack"},{"target_id":35,"type":"attack"},{"target_id":36,"type":"attack"},{"target_id":36,"type":"attack"},{"target_id":36,"type":"attack"},{"target_id":36,"type":"attack"},{"target_id":36,"type":"attack"},{"target_x":1166,"target_y":1423,"type":"move"},{"target_x":1135,"target_y":1372,"type":"move"},{"target_x":1104,"target_y":1321,"type":"move"},{"target_x":1071,"target_y":1271,"type":"move"},{"target_x":1040,"target_y":1220,"type":"move"},{"target_x":1009,"target_y":1169,"type":"move"},{"target_x":978,"target_y":1118,"type":"move"},{"target_x":947,"target_y":1067,"type":"move"},{"target_x":914,"target_y":1017,"type":"move"},{"target_x":883,"target_y":966,"type":"move"},{"target_x":852,"target_y":915,"type":"move"},{"target_x":821,"target_y":864,"type":"move"},{"target_id":37,"type":"attack"},{"target_id":37,"type":"attack"},{"target_id":37,"type":"attack"},{"target_id":37,"type":"attack"},{"target_id":37,"type":"attack"},{"target_id":37,"type":"attack"},{"target_id":37,"type":"attack"},{"target_id":37,"type":"attack"},{"target_id":37,"type":"attack"},{"target_id":37,"type":"attack"},{"target_id":37,"type":"attack"},{"target_id":37,"type":"attack"},{"target_id":37,"type":"attack"},{"target_id":37,"type":"attack"},{"target_id":37,"type":"attack"},{"target_id":37,"type":"attack"},{"target_id":37,"type":"attack"},{"target_id":37,"type":"attack"},{"target_id":37,"type":"attack"},{"target_id":37,"type":"attack"},{"target_id":37,"type":"attack"},{"target_id":37,"type":"attack"},{"target_id":37,"type":"attack"},{"target_id":37,"type":"attack"},{"target_id":37,"type":"attack"},{"target_x":780,"target_y":822,"type":"move"},{"target_id":38,"type":"attack"},{"target_id":38,"type":"attack"},{"target_id":38,"type":"attack"},{"target_id":38,"type":"attack"},{"target_id":38,"type":"attack"},{"target_id":38,"type":"attack"},{"target_id":38,"type":"attack"},{"target_id":38,"type":"attack"},{"target_id":39,"type":"attack"},{"target_id":39,"type":"attack"},{"target_id":39,"type":"attack"},{"target_id":39,"type":"attack"},{"target_id":40,"type":"attack"},{"target_id":40,"type":"attack"},{"target_id":40,"type":"attack"},{"target_id":40,"type":"attack"},{"target_id":40,"type":"attack"},{"target_id":40,"type":"attack"},{"target_id":40,"type":"attack"},{"target_id":40,"type":"attack"},{"target_id":40,"type":"attack"},{"target_id":41,"type":"attack"},{"target_id":41,"type":"attack"},{"target_id":41,"type":"attack"},{"target_id":41,"type":"attack"},{"target_id":41,"type":"attack"},{"target_id":41,"type":"attack"},{"target_id":42,"type":"attack"},{"target_id":42,"type":"attack"},{"target_id":42,"type":"attack"},{"target_id":42,"type":"attack"},{"target_id":42,"type":"attack"},{"target_id":42,"type":"attack"},{"target_id":42,"type":"attack"},{"target_id":42,"type":"attack"},{"target_id":42,"type":"attack"},{"target_id":42,"type":"attack"},{"target_id":42,"type":"attack"},{"target_id":43,"type":"attack"},{"target_id":43,"type":"attack"},{"target_id":43,"type":"attack"},{"target_id":43,"type":"attack"},{"target_id":43,"type":"attack"},{"target_id":43,"type":"attack"},{"target_id":43,"type":"attack"},{"target_id":43,"type":"attack"},{"target_id":43,"type":"attack"},{"target_id":43,"type":"attack"},{"target_id":44,"type":"attack"},{"target_id":44,"type":"attack"},{"target_id":44,"type":"attack"},{"target_id":44,"type":"attack"},{"target_id":44,"type":"attack"},{"target_x":785,"target_y":763,"type":"move"},{"target_x":790,"target_y":704,"type":"move"},{"target_x":795,"target_y":645,"type":"move"},{"target_x":800,"target_y":586,"type":"move"},{"target_x":805,"target_y":527,"type":"move"},{"target_x":809,"target_y":468,"type":"move"},{"target_x":813,"target_y":409,"type":"move"},{"target_x":817,"target_y":350,"type":"move"},{"target_x":817,"target_y":290,"type":"move"},{"target_id":45,"type":"attack"},{"target_id":45,"type":"attack"},{"target_id":45,"type":"attack"},{"target_id":45,"type":"attack"},{"target_id":45,"type":"attack"},{"target_id":45,"type":"attack"},{"target_id":45,"type":"attack"},{"target_id":45,"type":"attack"},{"target_id":45,"type":"attack"},{"target_id":45,"type":"attack"},{"target_id":45,"type":"attack"},{"target_id":45,"type":"attack"},{"target_id":45,"type":"attack"},{"target_id":45,"type":"attack"},{"target_id":45,"type":"attack"},{"target_id":45,"type":"attack"},{"target_id":45,"type":"attack"},{"target_id":45,"type":"attack"},{"target_id":45,"type":"attack"},{"target_id":45,"type":"attack"},{"target_id":45,"type":"attack"},{"target_id":45,"type":"attack"},{"target_id":45,"type":"attack"},{"target_id":45,"type":"attack"},{"target_id":45,"type":"attack"},{"target_id":45,"type":"attack"},{"target_id":45,"type":"attack"},{"target_id":46,"type":"attack"},{"target_id":46,"type":"attack"},{"target_id":46,"type":"attack"},{"target_id":46,"type":"attack"},{"target_id":46,"type":"attack"},{"target_id":46,"type":"attack"},{"target_id":46,"type":"attack"},{"target_id":46,"type":"attack"},{"target_id":46,"type":"attack"},{"target_id":46,"type":"attack"},{"target_id":46,"type":"attack"},{"target_id":46,"type":"attack"},{"target_id":46,"type":"attack"},{"target_id":47,"type":"attack"},{"target_id":47,"type":"attack"},{"target_id":47,"type":"attack"},{"target_id":47,"type":"attack"},{"target_id":47,"type":"attack"},{"target_id":47,"type":"attack"},{"target_id":47,"type":"attack"},{"target_id":47,"type":"attack"},{"target_id":47,"type":"attack"},{"target_id":48,"type":"attack"},{"target_id":48,"type":"attack"},{"target_id":48,"type":"attack"},{"target_id":48,"type":"attack"},{"target_id":48,"type":"attack"},{"target_id":48,"type":"attack"},{"target_id":48,"type":"attack"},{"target_id":48,"type":"attack"},{"target_id":48,"type":"attack"},{"target_id":48,"type":"attack"},{"target_id":48,"type":"attack"},{"target_id":49,"type":"attack"},{"target_id":49,"type":"attack"},{"target_id":49,"type":"attack"},{"target_id":49,"type":"attack"},{"target_id":49,"type":"attack"},{"target_id":49,"type":"attack"},{"target_id":49,"type":"attack"},{"target_id":49,"type":"attack"},{"target_id":49,"type":"attack"},{"target_id":49,"type":"attack"},{"target_id":49,"type":"attack"},{"target_id":49,"type":"attack"},{"target_id":50,"type":"attack"},{"target_id":50,"type":"attack"},{"target_id":50,"type":"attack"},{"target_id":50,"type":"attack"},{"target_id":50,"type":"attack"},{"target_id":50,"type":"attack"},{"target_id":50,"type":"attack"},{"target_id":50,"type":"attack"},{"target_id":50,"type":"attack"},{"target_id":50,"type":"attack"},{"target_x":858,"target_y":345,"type":"move"},{"target_x":902,"target_y":398,"type":"move"},{"target_x":943,"target_y":453,"type":"move"},{"target_x":984,"target_y":508,"type":"move"},{"target_x":1028,"target_y":561,"type":"move"},{"target_x":1069,"target_y":616,"type":"move"},{"target_x":1113,"target_y":669,"type":"move"},{"target_x":1154,"target_y":724,"type":"move"},{"target_x":1198,"target_y":777,"type":"move"},{"target_x":1239,"target_y":832,"type":"move"},{"target_id":51,"type":"attack"},{"target_id":51,"type":"attack"},{"target_id":51,"type":"attack"},{"target_id":51,"type":"attack"},{"target_id":51,"type":"attack"},{"target_id":51,"type":"attack"},{"target_id":51,"type":"attack"},{"target_id":51,"type":"attack"},{"target_id":51,"type":"attack"},{"target_id":51,"type":"attack"},{"target_id":51,"type":"attack"},{"target_id":51,"type":"attack"},{"target_id":51,"type":"attack"},{"target_id":51,"type":"attack"},{"target_id":51,"type":"attack"},{"target_id":51,"type":"attack"},{"target_id":51,"type":"attack"},{"target_id":51,"type":"attack"},{"target_id":51,"type":"attack"},{"target_id":51,"type":"attack"},{"target_id":51,"type":"attack"},{"target_x":1285,"target_y":873,"type":"move"},{"target_id":52,"type":"attack"},{"target_id":52,"type":"attack"},{"target_id":52,"type":"attack"},{"target_id":52,"type":"attack"},{"target_id":52,"type":"attack"},{"target_id":52,"type":"attack"},{"target_id":53,"type":"attack"},{"target_id":53,"type":"attack"},{"target_id":53,"type":"attack"},{"target_id":53,"type":"attack"},{"target_id":53,"type":"attack"},{"target_id":53,"type":"attack"},{"target_id":53,"type":"attack"},{"target_id":53,"type":"attack"},{"target_id":53,"type":"attack"},{"target_id":53,"type":"attack"},{"target_id":53,"type":"attack"},{"target_id":53,"type":"attack"},{"target_id":54,"type":"attack"},{"target_id":54,"type":"attack"},{"target_id":54,"type":"attack"},{"target_id":54,"type":"attack"},{"target_id":54,"type":"attack"},{"target_id":54,"type":"attack"},{"target_id":54,"type":"attack"},{"target_id":54,"type":"attack"},{"target_id":54,"type":"attack"},{"target_id":55,"type":"attack"},{"target_id":55,"type":"attack"},{"target_id":55,"type":"attack"},{"target_id":55,"type":"attack"},{"target_id":55,"type":"attack"},{"target_id":55,"type":"attack"},{"target_id":55,"type":"attack"},{"target_id":55,"type":"attack"},{"target_id":56,"type":"attack"},{"target_id":56,"type":"attack"},{"target_id":56,"type":"attack"},{"target_id":57,"type":"attack"},{"target_id":57,"type":"attack"},{"target_id":57,"type":"attack"},{"target_id":57,"type":"attack"},{"target_id":57,"type":"attack"},{"target_id":57,"type":"attack"},{"target_id":57,"type":"attack"},{"target_id":57,"type":"attack"},{"target_id":57,"type":"attack"},{"target_id":57,"type":"attack"},{"target_id":57,"type":"attack"},{"target_x":1221,"target_y":898,"type":"move"},{"target_x":1158,"target_y":926,"type":"move"},{"target_x":1094,"target_y":951,"type":"move"},{"target_x":1030,"target_y":976,"type":"move"},{"target_x":967,"target_y":1004,"type":"move"},{"target_x":903,"target_y":1029,"type":"move"},{"target_x":840,"target_y":1057,"type":"move"},{"target_x":776,"target_y":1082,"type":"move"},{"target_x":713,"target_y":1110,"type":"move"},{"target_x":649,"target_y":1135,"type":"move"},{"target_x":586,"target_y":1163,"type":"move"},{"target_x":522,"target_y":1188,"type":"move"},{"target_x":459,"target_y":1216,"type":"move"},{"target_x":395,"target_y":1241,"type":"move"},{"target_x":332,"target_y":1269,"type":"move"},{"target_id":58,"type":"attack"},{"target_id":58,"type":"attack"},{"target_id":58,"type":"attack"},{"target_id":58,"type":"attack"},{"target_id":58,"type":"attack"},{"target_id":58,"type":"attack"},{"target_id":58,"type":"attack"},{"target_id":58,"type":"attack"},{"target_id":58,"type":"attack"},{"target_id":58,"type":"attack"},{"target_id":58,"type":"attack"},{"target_id":58,"type":"attack"},{"target_id":58,"type":"attack"},{"target_id":58,"type":"attack"},{"target_id":58,"type":"attack"},{"target_id":58,"type":"attack"},{"target_id":58,"type":"attack"},{"target_id":59,"type":"attack"},{"target_id":59,"type":"attack"},{"target_id":59,"type":"attack"},{"target_id":59,"type":"attack"},{"target_id":59,"type":"attack"},{"target_id":60,"type":"attack"},{"target_id":60,"type":"attack"},{"target_id":60,"type":"attack"},{"target_id":60,"type":"attack"},{"target_id":60,"type":"attack"},{"target_id":61,"type":"attack"},{"target_id":61,"type":"attack"},{"target_id":61,"type":"attack"},{"target_id":61,"type":"attack"},{"target_id":61,"type":"attack"},{"target_id":61,"type":"attack"},{"target_id":61,"type":"attack"},{"target_id":61,"type":"attack"},{"target_id":61,"type":"attack"},{"target_id":62,"type":"attack"},{"target_id":62,"type":"attack"},{"target_id":62,"type":"attack"},{"target_id":62,"type":"attack"},{"target_id":62,"type":"attack"},{"target_id":62,"type":"attack"},{"target_id":62,"type":"attack"},{"target_id":62,"type":"attack"},{"target_id":62,"type":"attack"},{"target_id":62,"type":"attack"},{"target_id":62,"type":"attack"},{"target_x":400,"target_y":1258,"type":"move"},{"target_x":468,"target_y":1247,"type":"move"},{"target_x":536,"target_y":1236,"type":"move"},{"target_x":604,"target_y":1225,"type":"move"},{"target_x":672,"target_y":1215,"type":"move"},{"target_x":740,"target_y":1205,"type":"move"},{"target_x":808,"target_y":1196,"type":"move"},{"target_id":63,"type":"attack"},{"target_id":63,"type":"attack"},{"target_id":63,"type":"attack"},{"target_id":63,"type":"attack"},{"target_id":63,"type":"attack"},{"target_id":63,"type":"attack"},{"target_id":63,"type":"attack"},{"target_id":63,"type":"attack"},{"target_id":63,"type":"attack"},{"target_id":63,"type":"attack"},{"target_id":63,"type":"attack"},{"target_id":63,"type":"attack"},{"target_id":63,"type":"attack"},{"target_id":63,"type":"attack"},{"target_id":63,"type":"attack"},{"target_id":63,"type":"attack"},{"target_id":63,"type":"attack"},{"target_id":63,"type":"attack"},{"target_id":63,"type":"attack"},{"target_id":63,"type":"attack"},{"target_id":63,"type":"attack"},{"target_id":64,"type":"attack"},{"target_id":64,"type":"attack"},{"target_id":64,"type":"attack"},{"target_id":64,"type":"attack"},{"target_id":64,"type":"attack"},{"target_id":64,"type":"attack"},{"target_id":64,"type":"attack"},{"target_id":64,"type":"attack"},{"target_id":64,"type":"attack"},{"target_id":65,"type":"attack"},{"target_id":65,"type":"attack"},{"target_id":65,"type":"attack"},{"target_id":65,"type":"attack"},{"target_id":66,"type":"attack"},{"target_id":66,"type":"attack"},{"target_id":66,"type":"attack"},{"target_id":66,"type":"attack"},{"target_id":66,"type":"attack"},{"target_id":66,"type":"attack"},{"target_id":66,"type":"attack"},{"target_id":66,"type":"attack"},{"target_id":67,"type":"attack"},{"target_id":67,"type":"attack"},{"target_id":67,"type":"attack"},{"target_id":67,"type":"attack"},{"target_id":67,"type":"attack"},{"target_x":778,"target_y":1124,"type":"move"},{"target_x":748,"target_y":1052,"type":"move"},{"target_x":718,"target_y":980,"type":"move"},{"target_x":686,"target_y":909,"type":"move"},{"target_x":654,"target_y":838,"type":"move"},{"target_x":624,"target_y":766,"type":"move"},{"target_x":592,"target_y":695,"type":"move"},{"target_x":560,"target_y":624,"type":"move"},{"target_x":528,"target_y":553,"type":"move"},{"target_x":498,"target_y":481,"type":"move"},{"target_x":466,"target_y":410,"type":"move"},{"target_x":434,"target_y":339,"type":"move"},{"target_x":402,"target_y":268,"type":"move"},{"target_x":372,"target_y":196,"type":"move"},{"target_x":340,"target_y":125,"type":"move"},{"target_id":68,"type":"attack"},{"target_id":68,"type":"attack"},{"target_id":68,"type":"attack"},{"target_id":68,"type":"attack"},{"target_id":68,"type":"attack"},{"target_id":68,"type":"attack"},{"target_id":68,"type":"attack"},{"target_id":68,"type":"attack"},{"target_id":68,"type":"attack"},{"target_id":68,"type":"attack"},{"target_id":68,"type":"attack"},{"target_id":68,"type":"attack"},{"target_id":68,"type":"attack"},{"target_id":68,"type":"attack"},{"target_id":68,"type":"attack"},{"target_id":68,"type":"attack"},{"target_id":68,"type":"attack"},{"target_id":68,"type":"attack"},{"target_id":68,"type":"attack"},{"target_id":69,"type":"attack"},{"target_id":69,"type":"attack"},{"target_id":69,"type":"attack"},{"target_id":69,"type":"attack"},{"target_id":69,"type":"attack"},{"target_id":69,"type":"attack"},{"target_id":69,"type":"attack"},{"target_id":69,"type":"attack"},{"target_id":70,"type":"attack"},{"target_id":70,"type":"attack"},{"target_id":70,"type":"attack"},{"target_id":70,"type":"attack"},{"target_id":70,"type":"attack"},{"target_id":70,"type":"attack"},{"target_id":71,"type":"attack"},{"target_id":71,"type":"attack"},{"target_id":71,"type":"attack"},{"target_id":71,"type":"attack"},{"target_id":72,"type":"attack"},{"target_id":72,"type":"attack"},{"target_id":72,"type":"attack"},{"target_id":73,"type":"attack"},{"target_id":73,"type":"attack"},{"target_id":73,"type":"attack"},{"target_id":73,"type":"attack"},{"target_id":74,"type":"attack"},{"target_id":74,"type":"attack"},{"target_id":74,"type":"attack"},{"target_id":74,"type":"attack"},{"target_id":74,"type":"attack"},{"target_id":74,"type":"attack"},{"target_id":74,"type":"attack"},{"target_id":74,"type":"attack"},{"target_id":74,"type":"attack"},{"target_id":74,"type":"attack"},{"target_x":376,"target_y":194,"type":"move"},{"target_x":412,"target_y":263,"type":"move"},{"target_x":448,"target_y":332,"type":"move"},{"target_x":484,"target_y":401,"type":"move"},{"target_x":520,"target_y":470,"type":"move"},{"target_x":556,"target_y":539,"type":"move"},{"target_x":592,"target_y":608,"type":"move"},{"target_x":628,"target_y":677,"type":"move"},{"target_x":664,"target_y":746,"type":"move"},{"target_x":700,"target_y":815,"type":"move"},{"target_x":736,"target_y":884,"type":"move"},{"target_x":772,"target_y":953,"type":"move"},{"target_x":810,"target_y":1021,"type":"move"},{"target_x":846,"target_y":1090,"type":"move"},{"target_x":882,"target_y":1159,"type":"move"},{"target_x":918,"target_y":1228,"type":"move"},{"target_x":951,"target_y":1291,"type":"move"},{"target_id":75,"type":"attack"},{"target_id":75,"type":"attack"},{"target_id":75,"type":"attack"},{"target_id":75,"type":"attack"},{"target_id":75,"type":"attack"},{"target_id":75,"type":"attack"},{"target_id":75,"type":"attack"},{"target_id":75,"type":"attack"},{"target_id":75,"type":"attack"},{"target_id":75,"type":"attack"},{"target_id":75,"type":"attack"},{"target_id":75,"type":"attack"},{"target_id":75,"type":"attack"},{"target_id":75,"type":"attack"},{"target_id":75,"type":"attack"},{"target_id":75,"type":"attack"},{"target_id":75,"type":"attack"},{"target_id":76,"type":"attack"},{"target_id":76,"type":"attack"},{"target_id":76,"type":"attack"},{"target_id":76,"type":"attack"},{"target_id":76,"type":"attack"},{"target_id":76,"type":"attack"},{"target_id":76,"type":"attack"},{"target_id":76,"type":"attack"},{"target_id":76,"type":"attack"},{"target_id":77,"type":"attack"},{"target_id":77,"type":"attack"},{"target_id":77,"type":"attack"},{"target_id":77,"type":"attack"},{"target_id":78,"type":"attack"},{"target_id":78,"type":"attack"},{"target_id":78,"type":"attack"},{"target_id":78,"type":"attack"},{"target_id":78,"type":"attack"},{"target_id":78,"type":"attack"},{"target_id":78,"type":"attack"},{"target_id":78,"type":"attack"},{"target_id":79,"type":"attack"},{"target_id":79,"type":"attack"},{"target_id":79,"type":"attack"},{"target_id":79,"type":"attack"},{"target_id":79,"type":"attack"},{"target_id":79,"type":"attack"},{"target_id":79,"type":"attack"},{"target_id":80,"type":"attack"},{"target_id":80,"type":"attack"},{"target_id":80,"type":"attack"},{"target_id":80,"type":"attack"},{"target_id":80,"type":"attack"},{"target_id":80,"type":"attack"},{"target_id":80,"type":"attack"},{"target_id":80,"type":"attack"},{"target_id":81,"type":"attack"},{"target_id":81,"type":"attack"},{"target_id":81,"type":"attack"},{"target_x":981,"target_y":1219,"type":"move"},{"target_x":1011,"target_y":1147,"type":"move"},{"target_x":1043,"target_y":1076,"type":"move"},{"target_x":1075,"target_y":1005,"type":"move"},{"target_x":1105,"target_y":933,"type":"move"},{"target_x":1137,"target_y":862,"type":"move"},{"target_id":82,"type":"attack"},{"target_id":82,"type":"attack"},{"target_id":82,"type":"attack"},{"target_id":82,"type":"attack"},{"target_id":82,"type":"attack"},{"target_id":82,"type":"attack"},{"target_id":82,"type":"attack"},{"target_id":82,"type":"attack"},{"target_id":82,"type":"attack"},{"target_id":82,"type":"attack"},{"target_id":82,"type":"attack"},{"target_id":82,"type":"attack"},{"target_id":82,"type":"attack"},{"target_id":82,"type":"attack"},{"target_id":82,"type":"attack"},{"target_id":82,"type":"attack"},{"target_id":82,"type":"attack"},{"target_id":82,"type":"attack"},{"target_id":83,"type":"attack"},{"target_id":83,"type":"attack"},{"target_id":83,"type":"attack"},{"target_id":83,"type":"attack"},{"target_id":83,"type":"attack"},{"target_id":83,"type":"attack"},{"target_id":83,"type":"attack"},{"target_id":83,"type":"attack"},{"target_id":83,"type":"attack"},{"target_id":84,"type":"attack"},{"target_id":84,"type":"attack"},{"target_id":84,"type":"attack"},{"target_id":84,"type":"attack"},{"target_id":85,"type":"attack"},{"target_id":85,"type":"attack"},{"target_id":85,"type":"attack"},{"target_id":85,"type":"attack"},{"target_id":85,"type":"attack"},{"target_id":85,"type":"attack"},{"target_id":85,"type":"attack"},{"target_id":85,"type":"attack"},{"target_id":85,"type":"attack"},{"target_id":86,"type":"attack"},{"target_id":86,"type":"attack"},{"target_id":86,"type":"attack"},{"target_id":86,"type":"attack"},{"target_id":86,"type":"attack"},{"target_id":86,"type":"attack"},{"target_id":86,"type":"attack"},{"target_id":87,"type":"attack"},{"target_id":87,"type":"attack"},{"target_id":87,"type":"attack"},{"target_id":87,"type":"attack"},{"target_id":88,"type":"attack"},{"target_id":88,"type":"attack"},{"target_id":88,"type":"attack"},{"target_id":88,"type":"attack"},{"target_id":88,"type":"attack"},{"target_id":88,"type":"attack"},{"target_id":88,"type":"attack"},{"target_id":88,"type":"attack"},{"target_id":88,"type":"attack"},{"target_id":88,"type":"attack"},{"target_id":89,"type":"attack"},{"target_id":89,"type":"attack"},{"target_id":89,"type":"attack"},{"target_id":89,"type":"attack"},{"target_id":89,"type":"attack"},{"target_id":89,"type":"attack"},{"target_id":89,"type":"attack"},{"target_id":89,"type":"attack"},{"target_id":89,"type":"attack"},{"target_x":1207,"target_y":915,"type":"move"},{"target_x":1277,"target_y":968,"type":"move"},{"target_x":1347,"target_y":1021,"type":"move"},{"target_id":90,"type":"attack"},{"target_id":90,"type":"attack"},{"target_id":90,"type":"attack"},{"target_id":90,"type":"attack"},{"target_id":90,"type":"attack"},{"target_id":90,"type":"attack"},{"target_id":90,"type":"attack"},{"target_id":90,"type":"attack"},{"target_id":90,"type":"attack"},{"target_id":90,"type":"attack"},{"target_id":90,"type":"attack"},{"target_id":90,"type":"attack"},{"target_id":90,"type":"attack"},{"target_id":90,"type":"attack"},{"target_id":91,"type":"attack"},{"target_id":91,"type":"attack"},{"target_id":91,"type":"attack"},{"target_id":91,"type":"attack"},{"target_id":91,"type":"attack"},{"target_id":91,"type":"attack"},{"target_id":92,"type":"attack"},{"target_id":92,"type":"attack"},{"target_id":92,"type":"attack"},{"target_id":92,"type":"attack"},{"target_id":92,"type":"attack"},{"target_id":92,"type":"attack"},{"target_id":92,"type":"attack"},{"target_id":93,"type":"attack"},{"target_id":93,"type":"attack"},{"target_id":93,"type":"attack"},{"target_id":93,"type":"attack"},{"target_id":93,"type":"attack"},{"target_id":93,"type":"attack"},{"target_id":93,"type":"attack"},{"target_id":93,"type":"attack"},{"target_id":93,"type":"attack"},{"target_id":94,"type":"attack"},{"target_id":94,"type":"attack"},{"target_id":94,"type":"attack"},{"target_id":94,"type":"attack"},{"target_id":94,"type":"attack"},{"target_id":95,"type":"attack"},{"target_id":95,"type":"attack"},{"target_id":95,"type":"attack"},{"target_id":96,"type":"attack"},{"target_id":96,"type":"attack"},{"target_id":96,"type":"attack"},{"target_id":96,"type":"attack"},{"target_id":96,"type":"attack"},{"target_id":96,"type":"attack"},{"target_id":96,"type":"attack"},{"target_id":97,"type":"attack"},{"target_id":97,"type":"attack"},{"target_id":97,"type":"attack"},{"target_id":97,"type":"attack"},{"target_id":97,"type":"attack"},{"target_id":97,"type":"attack"},{"target_id":97,"type":"attack"},{"target_x":1268,"target_y":983,"type":"move"},{"target_x":1189,"target_y":945,"type":"move"},{"target_x":1110,"target_y":907,"type":"move"},{"target_x":1030,"target_y":871,"type":"move"},{"target_x":951,"target_y":833,"type":"move"},{"target_x":872,"target_y":795,"type":"move"},{"target_x":792,"target_y":759,"type":"move"},{"target_x":713,"target_y":721,"type":"move"},{"target_x":634,"target_y":683,"type":"move"},{"target_x":554,"target_y":647,"type":"move"},{"target_x":475,"target_y":609,"type":"move"},{"target_x":396,"target_y":571,"type":"move"},{"target_id":98,"type":"attack"},{"target_id":98,"type":"attack"},{"target_id":98,"type":"attack"},{"target_id":98,"type":"attack"},{"target_id":98,"type":"attack"},{"target_id":98,"type":"attack"},{"target_id":98,"type":"attack"},{"target_id":98,"type":"attack"},{"target_id":98,"type":"attack"},{"target_id":98,"type":"attack"},{"target_id":98,"type":"attack"},{"target_id":99,"type":"attack"},{"target_id":99,"type":"attack"},{"target_id":99,"type":"attack"},{"target_id":100,"type":"attack"},{"target_id":100,"type":"attack"},{"target_id":100,"type":"attack"},{"target_id":100,"type":"attack"},{"target_id":100,"type":"attack"},{"target_id":100,"type":"attack"},{"target_id":100,"type":"attack"},{"target_id":100,"type":"attack"},{"target_id":100,"type":"attack"},{"target_id":101,"type":"attack"},{"target_id":101,"type":"attack"},{"target_id":101,"type":"attack"},{"target_id":101,"type":"attack"},{"target_id":101,"type":"attack"},{"target_id":101,"type":"attack"},{"target_id":101,"type":"attack"},{"target_id":102,"type":"attack"},{"target_id":102,"type":"attack"},{"target_id":103,"type":"attack"},{"target_id":103,"type":"attack"},{"target_id":103,"type":"attack"},{"target_id":103,"type":"attack"},{"target_id":103,"type":"attack"},{"target_id":104,"type":"attack"},{"target_id":104,"type":"attack"},{"target_id":104,"type":"attack"},{"target_id":104,"type":"attack"},{"target_id":104,"type":"attack"},{"target_id":104,"type":"attack"},{"target_id":104,"type":"attack"},{"target_id":104,"type":"attack"},{"target_id":105,"type":"attack"},{"target_id":105,"type":"attack"},{"target_id":105,"type":"attack"},{"target_x":382,"target_y":639,"type":"move"},{"target_id":106,"type":"attack"},{"target_id":106,"type":"attack"},{"target_id":106,"type":"attack"},{"target_id":106,"type":"attack"},{"target_id":106,"type":"attack"},{"target_id":106,"type":"attack"},{"target_id":106,"type":"attack"},{"target_id":106,"type":"attack"},{"target_id":106,"type":"attack"},{"target_id":106,"type":"attack"},{"target_id":106,"type":"attack"},{"target_id":106,"type":"attack"},{"target_id":106,"type":"attack"},{"target_id":106,"type":"attack"},{"target_id":106,"type":"attack"},{"target_id":106,"type":"attack"},{"target_id":106,"type":"attack"},{"target_id":107,"type":"attack"},{"target_id":107,"type":"attack"},{"target_id":107,"type":"attack"},{"target_id":107,"type":"attack"},{"target_id":107,"type":"attack"},{"target_id":107,"type":"attack"},{"target_id":108,"type":"attack"},{"target_id":108,"type":"attack"},{"target_id":108,"type":"attack"},{"target_id":108,"type":"attack"},{"target_id":108,"type":"attack"},{"target_id":108,"type":"attack"},{"target_id":108,"type":"attack"},{"target_id":108,"type":"attack"},{"target_id":108,"type":"attack"},{"target_id":109,"type":"attack"},{"target_id":109,"type":"attack"},{"target_id":110,"type":"attack"},{"target_id":110,"type":"attack"},{"target_id":110,"type":"attack"},{"target_id":110,"type":"attack"},{"target_id":110,"type":"attack"},{"target_id":110,"type":"attack"},{"target_id":111,"type":"attack"},{"target_id":111,"type":"attack"},{"target_id":111,"type":"attack"},{"target_id":111,"type":"attack"},{"target_id":111,"type":"attack"},{"target_id":111,"type":"attack"},{"target_id":112,"type":"attack"},{"target_id":112,"type":"attack"},{"target_id":112,"type":"attack"},{"target_id":112,"type":"attack"},{"target_id":112,"type":"attack"},{"target_id":112,"type":"attack"},{"target_id":112,"type":"attack"},{"target_id":112,"type":"attack"},{"target_id":112,"type":"attack"},{"target_x":382,"target_y":736,"type":"move"},{"target_x":382,"target_y":833,"type":"move"},{"target_x":382,"target_y":930,"type":"move"},{"target_x":385,"target_y":1026,"type":"move"},{"target_x":385,"target_y":1123,"type":"move"},{"target_x":388,"target_y":1219,"type":"move"},{"target_x":388,"target_y":1316,"type":"move"},{"target_id":113,"type":"attack"},{"target_id":113,"type":"attack"},{"target_id":113,"type":"attack"},{"target_id":113,"type":"attack"},{"target_id":113,"type":"attack"},{"target_id":113,"type":"attack"},{"target_id":113,"type":"attack"},{"target_id":113,"type":"attack"},{"target_id":113,"type":"attack"},{"target_id":113,"type":"attack"},{"target_id":113,"type":"attack"},{"target_id":113,"type":"attack"},{"target_id":113,"type":"attack"},{"target_id":113,"type":"attack"},{"target_id":113,"type":"attack"},{"target_x":396,"target_y":1407,"type":"move"},{"target_id":114,"type":"attack"},{"target_id":114,"type":"attack"},{"target_id":114,"type":"attack"},{"target_id":114,"type":"attack"},{"target_id":114,"type":"attack"},{"target_id":115,"type":"attack"},{"target_id":115,"type":"attack"},{"target_id":115,"type":"attack"},{"target_id":116,"type":"attack"},{"target_id":116,"type":"attack"},{"target_id":116,"type":"attack"},{"target_id":116,"type":"attack"},{"target_id":117,"type":"attack"},{"target_id":117,"type":"attack"},{"target_id":117,"type":"attack"},{"target_id":118,"type":"attack"},{"target_id":118,"type":"attack"},{"target_id":118,"type":"attack"},{"target_id":118,"type":"attack"},{"target_id":118,"type":"attack"},{"target_id":118,"type":"attack"},{"target_id":118,"type":"attack"},{"target_id":118,"type":"attack"},{"target_id":118,"type":"attack"},{"target_x":343,"target_y":1326,"type":"move"},{"target_x":290,"target_y":1245,"type":"move"},{"target_x":240,"target_y":1162,"type":"move"},{"target_x":187,"target_y":1081,"type":"move"},{"target_id":119,"type":"attack"},{"target_id":119,"type":"attack"},{"target_id":119,"type":"attack"},{"target_id":119,"type":"attack"},{"target_id":119,"type":"attack"},{"target_id":119,"type":"attack"},{"target_id":119,"type":"attack"},{"target_id":119,"type":"attack"},{"target_id":119,"type":"attack"},{"target_id":119,"type":"attack"},{"target_id":119,"type":"attack"},{"target_id":119,"type":"attack"},{"target_id":119,"type":"attack"},{"target_id":119,"type":"attack"},{"target_id":119,"type":"attack"},{"target_id":120,"type":"attack"},{"target_id":120,"type":"attack"},{"target_id":120,"type":"attack"},{"target_id":120,"type":"attack"},{"target_id":120,"type":"attack"},{"target_id":120,"type":"attack"},{"target_id":121,"type":"attack"},{"target_id":121,"type":"attack"},{"target_id":121,"type":"attack"},{"target_id":122,"type":"attack"},{"target_id":122,"type":"attack"},{"target_id":122,"type":"attack"},{"target_id":123,"type":"attack"},{"target_id":123,"type":"attack"},{"target_id":123,"type":"attack"},{"target_id":123,"type":"attack"},{"target_id":123,"type":"attack"},{"target_id":123,"type":"attack"},{"target_id":123,"type":"attack"},{"target_id":123,"type":"attack"},{"target_id":124,"type":"attack"},{"target_id":124,"type":"attack"},{"target_id":124,"type":"attack"},{"target_id":124,"type":"attack"},{"target_id":124,"type":"attack"},{"target_id":124,"type":"attack"},{"target_id":124,"type":"attack"},{"target_id":124,"type":"attack"},{"target_id":125,"type":"attack"},{"target_id":125,"type":"attack"},{"target_id":125,"type":"attack"},{"target_id":125,"type":"attack"},{"target_id":125,"type":"attack"},{"target_id":125,"type":"attack"},{"target_id":126,"type":"attack"},{"target_id":126,"type":"attack"},{"target_id":126,"type":"attack"},{"target_id":126,"type":"attack"},{"target_id":126,"type":"attack"},{"target_id":126,"type":"attack"},{"target_id":126,"type":"attack"},{"target_x":184,"target_y":985,"type":"move"},{"target_x":181,"target_y":889,"type":"move"},{"target_x":181,"target_y":799,"type":"move"},{"target_id":127,"type":"attack"},{"target_id":127,"type":"attack"},{"target_id":127,"type":"attack"},{"target_id":127,"type":"attack"},{"target_id":127,"type":"attack"},{"target_id":127,"type":"attack"},{"target_id":127,"type":"attack"},{"target_id":127,"type":"attack"},{"target_id":127,"type":"attack"},{"target_id":127,"type":"attack"},{"target_id":127,"type":"attack"},{"target_id":127,"type":"attack"},{"target_id":127,"type":"attack"},{"target_id":127,"type":"attack"},{"target_id":127,"type":"attack"},{"target_id":128,"type":"attack"},{"target_id":128,"type":"attack"},{"target_id":128,"type":"attack"},{"target_id":128,"type":"attack"},{"target_id":129,"type":"attack"},{"target_id":129,"type":"attack"},{"target_id":129,"type":"attack"},{"target_id":129,"type":"attack"},{"target_id":130,"type":"attack"},{"target_id":130,"type":"attack"},{"target_id":130,"type":"attack"},{"target_id":130,"type":"attack"},{"target_id":130,"type":"attack"},{"target_id":130,"type":"attack"},{"target_id":130,"type":"attack"},{"target_id":131,"type":"attack"},{"target_id":131,"type":"attack"},{"target_id":131,"type":"attack"},{"target_id":131,"type":"attack"},{"target_id":131,"type":"attack"},{"target_id":131,"type":"attack"},{"target_id":131,"type":"attack"},{"target_id":132,"type":"attack"},{"target_id":132,"type":"attack"},{"target_id":132,"type":"attack"},{"target_id":132,"type":"attack"},{"target_id":132,"type":"attack"},{"target_id":132,"type":"attack"},{"target_id":132,"type":"attack"},{"target_id":132,"type":"attack"},{"target_x":266,"target_y":753,"type":"move"},{"target_x":336,"target_y":718,"type":"move"},{"target_id":133,"type":"attack"},{"target_id":133,"type":"attack"},{"target_id":133,"type":"attack"},{"target_id":133,"type":"attack"},{"target_id":133,"type":"attack"},{"target_id":133,"type":"attack"},{"target_id":133,"type":"attack"},{"target_id":133,"type":"attack"},{"target_id":133,"type":"attack"},{"target_id":133,"type":"attack"},{"target_id":133,"type":"attack"},{"target_id":133,"type":"attack"},{"target_id":134,"type":"attack"},{"target_id":134,"type":"attack"},{"target_id":134,"type":"attack"},{"target_id":135,"type":"attack"},{"target_id":135,"type":"attack"},{"target_id":135,"type":"attack"},{"target_id":135,"type":"attack"},{"target_id":135,"type":"attack"},{"target_id":135,"type":"attack"},{"target_id":135,"type":"attack"},{"target_id":135,"type":"attack"},{"target_id":136,"type":"attack"},{"target_id":136,"type":"attack"},{"target_id":136,"type":"attack"},{"target_id":136,"type":"attack"},{"target_id":136,"type":"attack"},{"target_id":136,"type":"attack"},{"target_id":137,"type":"attack"},{"target_id":137,"type":"attack"},{"target_id":137,"type":"attack"},{"target_id":137,"type":"attack"},{"target_id":137,"type":"attack"},{"target_id":138,"type":"attack"},{"target_id":138,"type":"attack"},{"target_id":138,"type":"attack"},{"target_id":138,"type":"attack"},{"target_id":138,"type":"attack"},{"target_id":138,"type":"attack"},{"target_id":138,"type":"attack"},{"target_id":139,"type":"attack"},{"target_id":139,"type":"attack"},{"target_id":139,"type":"attack"},{"target_id":139,"type":"attack"},{"target_id":140,"type":"attack"},{"target_id":140,"type":"attack"},{"target_id":140,"type":"attack"},{"target_id":140,"type":"attack"},{"target_id":140,"type":"attack"},{"target_x":318,"target_y":623,"type":"move"},{"target_x":300,"target_y":528,"type":"move"},{"target_x":282,"target_y":433,"type":"move"},{"target_x":264,"target_y":338,"type":"move"},{"target_x":247,"target_y":243,"type":"move"},{"target_x":231,"target_y":148,"type":"move"},{"target_id":141,"type":"attack"},{"target_id":141,"type":"attack"},{"target_id":141,"type":"attack"},{"target_id":141,"type":"attack"},{"target_id":141,"type":"attack"},{"target_id":141,"type":"attack"},{"target_id":141,"type":"attack"},{"target_id":141,"type":"attack"},{"target_id":141,"type":"attack"},{"target_id":141,"type":"attack"},{"target_id":141,"type":"attack"},{"target_id":141,"type":"attack"},{"target_id":141,"type":"attack"},{"target_id":142,"type":"attack"},{"target_id":142,"type":"attack"},{"target_id":142,"type":"attack"},{"target_id":142,"type":"attack"},{"target_id":143,"type":"attack"},{"target_id":143,"type":"attack"},{"target_id":143,"type":"attack"},{"target_id":143,"type":"attack"},{"target_id":143,"type":"attack"},{"target_id":143,"type":"attack"},{"target_id":144,"type":"attack"},{"target_id":144,"type":"attack"},{"target_id":144,"type":"attack"},{"target_id":144,"type":"attack"},{"target_id":144,"type":"attack"},{"target_id":144,"type":"attack"},{"target_id":145,"type":"attack"},{"target_id":145,"type":"attack"}]}